modulegraph/__init__.py
modulegraph/__main__.py
modulegraph/find_modules.py
modulegraph/modulegraph.py
modulegraph/util.py
modulegraph/zipio.py
modulegraph-0.19.4.dist-info/LICENSE
modulegraph-0.19.4.dist-info/METADATA
modulegraph-0.19.4.dist-info/WHEEL
modulegraph-0.19.4.dist-info/entry_points.txt
modulegraph-0.19.4.dist-info/top_level.txt
modulegraph-0.19.4.dist-info/zip-safe
modulegraph-0.19.4.dist-info/RECORD
