Metadata-Version: 2.1
Name: modulegraph
Version: 0.19.4
Summary: Python module dependency analysis tool
Home-page: http://github.com/ronaldoussoren/modulegraph
Download-URL: http://pypi.python.org/pypi/modulegraph
Author: Ronald Oussoren
Author-email: ronaldoussoren@mac.com
Maintainer: Ronald Oussoren
Maintainer-email: ronaldoussoren@mac.com
License: MIT
Keywords: import,,dependencies
Platform: any
Classifier: Intended Audience :: Developers
Classifier: License :: OSI Approved :: MIT License
Classifier: Programming Language :: Python
Classifier: Programming Language :: Python :: 2
Classifier: Programming Language :: Python :: 2.7
Classifier: Programming Language :: Python :: 3
Classifier: Programming Language :: Python :: 3.4
Classifier: Programming Language :: Python :: 3.5
Classifier: Programming Language :: Python :: 3.6
Classifier: Programming Language :: Python :: 3.7
Classifier: Programming Language :: Python :: 3.8
Classifier: Programming Language :: Python :: 3.9
Classifier: Programming Language :: Python :: 3.10
Classifier: Programming Language :: Python :: 3.11
Classifier: Topic :: Software Development :: Libraries :: Python Modules
Classifier: Topic :: Software Development :: Build Tools
License-File: LICENSE
Project-URL: Documentation, https://modulegraph.readthedocs.io/en/latest/
Project-URL: Issue tracker, https://github.com/ronaldoussoren/modulegraph/issues
Project-URL: Repository, https://github.com/ronaldoussoren/modulegraph
Requires-Dist: altgraph (>=0.15)
Requires-Dist: setuptools
